myutils/__init__.py
myutils/plotting.py
vwoodutils-0.4.1.dist-info/METADATA
vwoodutils-0.4.1.dist-info/WHEEL
vwoodutils-0.4.1.dist-info/top_level.txt
vwoodutils-0.4.1.dist-info/RECORD
