Metadata-Version: 2.1
Name: vwoodutils
Version: 0.4.1
Summary: My python utilities
Author: vwood
Author-email: vwood <spam@vwood.org>
